MANIFEST.in
README.md
setup.cfg
setup.py
camel_race.egg-info/PKG-INFO
camel_race.egg-info/SOURCES.txt
camel_race.egg-info/dependency_links.txt
camel_race.egg-info/entry_points.txt
camel_race.egg-info/requires.txt
camel_race.egg-info/top_level.txt
games/__init__.py
games/cli_game.py
games/cli_game_launcher.py
games/games_exceptions.py
games/play.py
games/camels_race/__init__.py
games/camels_race/camel.py
games/camels_race/camel_weapon.py
games/camels_race/camels_race_exceptions.py
games/camels_race/config.json
games/camels_race/constants.py
games/camels_race/race_game.py
games/camels_race/utils.py