Metadata-Version: 1.0
Name: camel-race
Version: 1.0.9
Summary: Camel Race ascii game
Home-page: https://dummystack.com
Author: Ibrahim Menem
Author-email: ibrahimmenem@gmail.com
License: UNKNOWN
Platform: UNKNOWN
